{
  "db_name": "SQLite",
  "query": "SELECT id, name, category FROM tags WHERE name = ? COLLATE NOCASE AND category IS NULL",
  "describe": {
    "columns": [
      {
        "name": "id",
        "ordinal": 0,
        "type_info": "Text"
      },
      {
        "name": "name",
        "ordinal": 1,
        "type_info": "Text"
      },
      {
        "name": "category",
        "ordinal": 2,
        "type_info": "Text"
      }
    ],
    "parameters": {
      "Right": 1
    },
    "nullable": [
      false,
      false,
      true
    ]
  },
  "hash": "46443f1d21eed48cc9cda0ee703fcdd690cf3bc98f47827c74aa38c17cf84c88"
}
